scrapeit_cloud/__init__.py
scrapeit_cloud/__version__.py
scrapeit_cloud/client.py
scrapeit_cloud/default_headers.py
scrapeit_cloud-1.0.2.dist-info/LICENSE
scrapeit_cloud-1.0.2.dist-info/METADATA
scrapeit_cloud-1.0.2.dist-info/WHEEL
scrapeit_cloud-1.0.2.dist-info/top_level.txt
scrapeit_cloud-1.0.2.dist-info/RECORD
